{
  "modules": [
    {
      "module_name": "bufbuild/protovalidate",
      "latest_reference": "v0.1.12"
    },
    {
      "module_name": "bufbuild/protovalidate-testing",
      "latest_reference": "v0.1.12"
    },
    {
      "module_name": "cncf/xds",
      "latest_reference": "e9ce68804cb4e64cab5a52e3c8baf840d4ff87b7"
    },
    {
      "module_name": "envoyproxy/envoy",
      "latest_reference": "b066af3149a3c67a30c7ad8677c3a2b98f278f31"
    },
    {
      "module_name": "envoyproxy/protoc-gen-validate",
      "latest_reference": "fab737efbb4b4d03e7c771393708f75594b121e4"
    },
    {
      "module_name": "gogo/protobuf",
      "latest_reference": "f67b8970b736e53dbd7d0a27146c8f1ac52f74e5"
    },
    {
      "module_name": "googleapis/googleapis",
      "latest_reference": "d39c91b3ac0abec1490ef00010107355a4dae317"
    },
    {
      "module_name": "googlechrome/lighthouse",
      "latest_reference": "6d9b11eb325859c7a1328b8e44be63e6c7f0b3cc"
    },
    {
      "module_name": "grpc-ecosystem/grpc-gateway",
      "latest_reference": "06fae32b118ceb06e71790117a41c323f70de03e"
    },
    {
      "module_name": "grpc/grpc",
      "latest_reference": "a0e6d670f8e6357305698fbfd06b4fbcb3b3d63b"
    },
    {
      "module_name": "opencensus/opencensus",
      "latest_reference": "1664cc961550be8f3058ddd29390350242f44f1f"
    },
    {
      "module_name": "opentelemetry/opentelemetry",
      "latest_reference": "4967b51b5cb29f725978362b9d413bae1dbb641c"
    },
    {
      "module_name": "prometheus/client-model",
      "latest_reference": "91c3945f2cfbfb9040e34a0b6764d804b5a5a490"
    },
    {
      "module_name": "protocolbuffers/wellknowntypes",
      "latest_reference": "v23.3"
    }
  ]
}