{
  "modules": [
    {
      "module_name": "bufbuild/confluent",
      "latest_reference": "18c83a31d7e710e1b8978fca46a392381bf2fa7e"
    },
    {
      "module_name": "bufbuild/protovalidate",
      "latest_reference": "v0.5.4"
    },
    {
      "module_name": "bufbuild/protovalidate-testing",
      "latest_reference": "v0.5.4"
    },
    {
      "module_name": "bufbuild/reflect",
      "latest_reference": "6c3bd3d519305521d5c133f580d919d91f8a5900"
    },
    {
      "module_name": "cncf/xds",
      "latest_reference": "0fa0005c9caaaae56e586ec2c6c26ef93704d29f"
    },
    {
      "module_name": "envoyproxy/envoy",
      "latest_reference": "15f199651348e486f08762fe62bfe3bda1c4c508"
    },
    {
      "module_name": "envoyproxy/protoc-gen-validate",
      "latest_reference": "cf13b5702b6ab4a70f90037a555557a44ff52abe"
    },
    {
      "module_name": "gogo/protobuf",
      "latest_reference": "f67b8970b736e53dbd7d0a27146c8f1ac52f74e5"
    },
    {
      "module_name": "google/cel-spec",
      "latest_reference": "v0.14.0"
    },
    {
      "module_name": "googleapis/googleapis",
      "latest_reference": "40203ca1880849480bbff7b8715491060bbccdf1"
    },
    {
      "module_name": "googlechrome/lighthouse",
      "latest_reference": "ed04b10ccfa4e82ee5cd5b437e474a12c1ba52d0"
    },
    {
      "module_name": "grpc-ecosystem/grpc-gateway",
      "latest_reference": "2a111f01f0bcc2703d380ab1aad8ba9a4b6228d0"
    },
    {
      "module_name": "grpc/grpc",
      "latest_reference": "5ba669a3292d2b2808be40f08e15185567e223d8"
    },
    {
      "module_name": "opencensus/opencensus",
      "latest_reference": "1664cc961550be8f3058ddd29390350242f44f1f"
    },
    {
      "module_name": "opentelemetry/opentelemetry",
      "latest_reference": "c451441d7b73f702d1647574c730daf7786f188c"
    },
    {
      "module_name": "prometheus/client-model",
      "latest_reference": "d56cd794bca9543da8cc93e95432cd64d5f99635"
    },
    {
      "module_name": "protocolbuffers/wellknowntypes",
      "latest_reference": "v25.2"
    }
  ]
}