{
  "modules": [
    {
      "module_name": "bufbuild/confluent",
      "latest_reference": "bd2b70874fbf6e4654b9127fec37b0ef3be8d45a"
    },
    {
      "module_name": "bufbuild/protovalidate",
      "latest_reference": "v0.6.4"
    },
    {
      "module_name": "bufbuild/protovalidate-testing",
      "latest_reference": "v0.6.4"
    },
    {
      "module_name": "bufbuild/reflect",
      "latest_reference": "66bfea7a86e10b3cb421c4b90201b74becda519f"
    },
    {
      "module_name": "cncf/xds",
      "latest_reference": "555b57ec207be86f811fb0c04752db6f85e3d7e2"
    },
    {
      "module_name": "envoyproxy/envoy",
      "latest_reference": "c668081ba0ab0781ca08b7227c52a87602f03244"
    },
    {
      "module_name": "envoyproxy/protoc-gen-validate",
      "latest_reference": "d338e0a7c5a3aa016a2b3680edd60b257f2df0df"
    },
    {
      "module_name": "gogo/protobuf",
      "latest_reference": "f67b8970b736e53dbd7d0a27146c8f1ac52f74e5"
    },
    {
      "module_name": "google/cel-spec",
      "latest_reference": "v0.15.0"
    },
    {
      "module_name": "googleapis/googleapis",
      "latest_reference": "ac90fa9958bd6f7622674f52f77e4dc01d98bee8"
    },
    {
      "module_name": "googlechrome/lighthouse",
      "latest_reference": "32cafcbf9229dd6b613783f742e008ca112a7a17"
    },
    {
      "module_name": "googlecloudplatform/bq-schema-api",
      "latest_reference": "78b6998919e338fec9f4a251bc334d69e030e118"
    },
    {
      "module_name": "grpc-ecosystem/grpc-gateway",
      "latest_reference": "2576b4ff0a15de7112cdaacb91059f41aa596493"
    },
    {
      "module_name": "grpc/grpc",
      "latest_reference": "43b6617ea5a79de6b0c7c06f3eb8e84a6452a215"
    },
    {
      "module_name": "opencensus/opencensus",
      "latest_reference": "1664cc961550be8f3058ddd29390350242f44f1f"
    },
    {
      "module_name": "opentelemetry/opentelemetry",
      "latest_reference": "bd7cf55b6d45f3c587d2131b68a7e5a501bdb10c"
    },
    {
      "module_name": "prometheus/client-model",
      "latest_reference": "a534ba6f2551174b8a7792843b58beebeda5fbd4"
    },
    {
      "module_name": "protocolbuffers/gofeatures",
      "latest_reference": "v1.34.2"
    },
    {
      "module_name": "protocolbuffers/wellknowntypes",
      "latest_reference": "v27.1"
    }
  ]
}